bibleit/__init__.py
bibleit/__main__.py
bibleit/bible.py
bibleit/config.py
bibleit/context.py
bibleit/normalize.py
bibleit/repl.py
bibleit/screen.py
bibleit/test_bible.py
bibleit/command/__init__.py
bibleit/command/args.py
bibleit/command/core.py
bibleit/command/set.py
bibleit/translations/acf
bibleit/translations/ara
bibleit/translations/kjv
bibleit/translations/lut
bibleit/translations/niv
bibleit/translations/nvi
bibleit/translations/nvie
bibleit-0.0.26.dist-info/METADATA
bibleit-0.0.26.dist-info/WHEEL
bibleit-0.0.26.dist-info/licenses/LICENSE
bibleit-0.0.26.dist-info/RECORD
