Metadata-Version: 2.3
Name: bibleit
Version: 0.0.26
Summary: Interactive bible reading
Project-URL: Homepage, https://github.com/fmamud/bibleit
Project-URL: Bug Tracker, https://github.com/fmamud/bibleit/issues
Author-email: Felipe Mamud <trovatti@gmail.com>
License: MIT License
License-File: LICENSE
Classifier: License :: OSI Approved :: MIT License
Classifier: Operating System :: OS Independent
Classifier: Programming Language :: Python :: 3
Requires-Python: >=3.10
Requires-Dist: gnureadline; platform_system == 'Darwin'
Provides-Extra: dev
Requires-Dist: black; extra == 'dev'
Requires-Dist: flake8; extra == 'dev'
Requires-Dist: requests; extra == 'dev'
